ltpylib/__init__.py
ltpylib/aws.py
ltpylib/checks.py
ltpylib/chrome.py
ltpylib/cli.py
ltpylib/collect.py
ltpylib/colors.py
ltpylib/common_types.py
ltpylib/compare.py
ltpylib/concurrency_helper.py
ltpylib/configs.py
ltpylib/configs_compat.py
ltpylib/datadog.py
ltpylib/datadog_api.py
ltpylib/dates.py
ltpylib/db_helper.py
ltpylib/dicts.py
ltpylib/enums.py
ltpylib/files.py
ltpylib/files_prettifier.py
ltpylib/filters.py
ltpylib/gitrepos.py
ltpylib/htmlparser.py
ltpylib/inputs.py
ltpylib/jenkins.py
ltpylib/jenkins_api.py
ltpylib/jenkins_types.py
ltpylib/jira.py
ltpylib/jira_api.py
ltpylib/jira_api_types.py
ltpylib/logs.py
ltpylib/looker_api.py
ltpylib/macos.py
ltpylib/mvnutil.py
ltpylib/numbers_util.py
ltpylib/opts.py
ltpylib/opts_actions.py
ltpylib/output.py
ltpylib/patterns.py
ltpylib/procs.py
ltpylib/reflections.py
ltpylib/requests_helper.py
ltpylib/resources.py
ltpylib/runners.py
ltpylib/search.py
ltpylib/sorting.py
ltpylib/sqlite_helper.py
ltpylib/stash_api.py
ltpylib/stash_types.py
ltpylib/strconverters.py
ltpylib/strings.py
ltpylib/templates.py
ltpylib/terminals.py
ltpylib/timing.py
ltpylib/versions.py
ltpylib/xmlparser.py
ltpylibtests/__init__.py
ltpylibtests/test_checks.py
ltpylibtests/test_collect.py
ltpylibtests/test_common_types.py
ltpylibtests/test_files.py
ltpylibtests/test_mvnutil.py
ltpylibtests/test_strings.py
ltpylibtests/testing_utils.py
ltpylib-1.11.0.dist-info/LICENSE
ltpylib-1.11.0.dist-info/METADATA
ltpylib-1.11.0.dist-info/WHEEL
ltpylib-1.11.0.dist-info/entry_points.txt
ltpylib-1.11.0.dist-info/top_level.txt
ltpylib-1.11.0.dist-info/RECORD
